Workbook
Name aporte: 'APP INVEST.'!$D$13
Name Patrimonio: 'APP INVEST.'!$D$16
Name Qtd_anos: 'APP INVEST.'!$D$14
Name rendimento_carteira: 'APP INVEST.'!$D$9
Name Salario: 'APP INVEST.'!$D$8
Name Sugestao_Invstimento: 'APP INVEST.'!$D$10
Name Taxa_mensal: 'APP INVEST.'!$D$15

Sheet APP INVEST.
B7: CONFIGURAÇÕES INICIAIS
B8: Sálario
B9: Rendimento Carteira
B10: Sugestão de Investimento (30%) | D10: =(D8*30%) -> 0
B12: INVESTIMENTO MENSAL
B13: Quanto investir por mês?
B14: Por Quantos Anos?
B15: Taxa de Rendimento mensal?
B16: Patrimônio Acumulado? | D16: =FV(Taxa_mensal,Qtd_anos*12,aporte*-1) -> 0
B17: Dividendos Mensais? | D17: =(Patrimonio*rendimento_carteira) -> 0
B19: CENÁRIOS | D19: DIVIDENDOS
A20: 2 | B20: Quanto em 2 Anos? | C20: =FV($D$15,$A20*12,$D$13*-1) -> 0 | D20: =(C20*rendimento_carteira) -> 0
A21: 5 | B21: Quanto em 5 Anos? | C21: =FV($D$15,$A21*12,$D$13*-1) -> 0 | D21: =(C21*rendimento_carteira) -> 0
A22: 10 | B22: Quanto em 10 Anos? | C22: =FV($D$15,$A22*12,$D$13*-1) -> 0 | D22: =(C22*rendimento_carteira) -> 0
A23: 20 | B23: Quanto em 20 Anos? | C23: =FV($D$15,$A23*12,$D$13*-1) -> 0 | D23: =(C23*rendimento_carteira) -> 0
A24: 30 | B24: Quanto em 30 Anos? | C24: =FV($D$15,$A24*12,$D$13*-1) -> 0 | D24: =(C24*rendimento_carteira) -> 0
B26: Perfil
B27: Valor a ser investido por mês | C27: =aporte -> 0
B29: Tipo de FII | C29: Percentual Sugerido | D29: Valores
B30: Papel | C30: =IFERROR(VLOOKUP($C$26&"-"&B30,Planilha2!A:D,4,0),"") | D30: =IFERROR((C30*$C$27),"")
B31: Tijolo | C31: =IFERROR(VLOOKUP($C$26&"-"&B31,Planilha2!A:D,4,0),"") | D31: =IFERROR((C31*$C$27),"")
B32: Híbridos | C32: =IFERROR(VLOOKUP($C$26&"-"&B32,Planilha2!A:D,4,0),"") | D32: =IFERROR((C32*$C$27),"")
B33: FOFs | C33: =IFERROR(VLOOKUP($C$26&"-"&B33,Planilha2!A:D,4,0),"") | D33: =IFERROR((C33*$C$27),"")
B34: Desenvolvimento | C34: =IFERROR(VLOOKUP($C$26&"-"&B34,Planilha2!A:D,4,0),"") | D34: =IFERROR((C34*$C$27),"")
B35: Hotelarias | C35: =IFERROR(VLOOKUP($C$26&"-"&B35,Planilha2!A:D,4,0),"") | D35: =IFERROR((C35*$C$27),"")
B36: Total | C36: =SUM(C30:C35) -> 0 | D36: =SUM(D30:D35) -> 0
B50: Dicas de onde buscar FIIs | C50: Site Oficial
B51: 🥇 1) Funds Explorer | C51: https://www.fundsexplorer.com.br
B52: 🥈 2) Status Invest | C52: https://statusinvest.com.br
B53: 🥉 3) FIIs.com.br | C53: https://fiis.com.br

Sheet Planilha2
A2: Chave | B2: Perfil | C2: Tipo de FII | D2: %
A3: =B3&"-"&C3 -> Conservador-Papel | B3: Conservador | C3: Papel | D3: 0.3
A4: =B4&"-"&C4 -> Conservador-Tijolo | B4: Conservador | C4: Tijolo | D4: 0.5
A5: =B5&"-"&C5 -> Conservador-Híbridos | B5: Conservador | C5: Híbridos | D5: 0.1
A6: =B6&"-"&C6 -> Conservador-FOFs | B6: Conservador | C6: FOFs | D6: 0.1
A7: =B7&"-"&C7 -> Conservador-Desenvolvimento | B7: Conservador | C7: Desenvolvimento | D7: 0
A8: =B8&"-"&C8 -> Conservador-Hotelarias | B8: Conservador | C8: Hotelarias | D8: 0
A9: =B9&"-"&C9 -> Moderado-Papel | B9: Moderado | C9: Papel | D9: 0.32
A10: =B10&"-"&C10 -> Moderado-Tijolo | B10: Moderado | C10: Tijolo | D10: 0.35
A11: =B11&"-"&C11 -> Moderado-Híbridos | B11: Moderado | C11: Híbridos | D11: 0.08
A12: =B12&"-"&C12 -> Moderado-FOFs | B12: Moderado | C12: FOFs | D12: 0.05
A13: =B13&"-"&C13 -> Moderado-Desenvolvimento | B13: Moderado | C13: Desenvolvimento | D13: 0.1
A14: =B14&"-"&C14 -> Moderado-Hotelarias | B14: Moderado | C14: Hotelarias | D14: 0.1
... A20: =B20&"-"&C20 -> Agressivo-Hotelarias | B20: Agressivo | C20: Hotelarias | D20: 0.1
